docs/conf.py
soulsgym/__init__.py
soulsgym/exception.py
soulsgym/core/__init__.py
soulsgym/core/game_input.py
soulsgym/core/game_state.py
soulsgym/core/memory_manipulator.py
soulsgym/core/static.py
soulsgym/core/utils.py
soulsgym/core/data/darksouls3/actions.yaml
soulsgym/core/data/darksouls3/addresses.yaml
soulsgym/core/data/darksouls3/animations.yaml
soulsgym/core/data/darksouls3/bonfires.yaml
soulsgym/core/data/darksouls3/coordinates.yaml
soulsgym/core/data/darksouls3/keys.yaml
soulsgym/core/data/darksouls3/player_stats.yaml
soulsgym/core/data/eldenring/actions.yaml
soulsgym/core/data/eldenring/addresses.yaml
soulsgym/core/data/eldenring/animations.yaml
soulsgym/core/data/eldenring/bonfires.yaml
soulsgym/core/data/eldenring/coordinates.yaml
soulsgym/core/data/eldenring/keys.yaml
soulsgym/core/data/eldenring/player_stats.yaml
soulsgym/core/game_window/__init__.py
soulsgym/core/game_window/game_window.py
soulsgym/core/game_window/window_capture.py
soulsgym/core/game_window/_C/window_capture.pyd
soulsgym/core/speedhack/__init__.py
soulsgym/core/speedhack/speedhack.py
soulsgym/core/speedhack/_C/SpeedHackDLL.dll
soulsgym/envs/__init__.py
soulsgym/envs/soulsenv.py
soulsgym/envs/config/iudex.yaml
soulsgym/envs/darksouls3/__init__.py
soulsgym/envs/darksouls3/iudex.py
soulsgym/envs/darksouls3/vordt.py
soulsgym/games/__init__.py
soulsgym/games/darksouls3.py
soulsgym/games/eldenring.py
soulsgym/games/game.py
tests/__init__.py
tests/test.py
tests/utils.py
tests/darksouls3/__init__.py
tests/darksouls3/integration_tests/__init__.py
tests/darksouls3/integration_tests/test_envs.py
tests/darksouls3/unit_tests/__init__.py
tests/darksouls3/unit_tests/test_game.py
tests/eldenring/__init__.py
tests/eldenring/test_game.py
soulsgym-1.1.0.dist-info/LICENSE
soulsgym-1.1.0.dist-info/METADATA
soulsgym-1.1.0.dist-info/WHEEL
soulsgym-1.1.0.dist-info/top_level.txt
soulsgym-1.1.0.dist-info/RECORD
