Metadata-Version: 2.1
Name: soulsgym
Version: 1.1.0
Summary: Gymnasium extension for DarkSouls III
Author-email: Martin Schuck <real.amacati@gmail.com>
License: Copyright 2022 Martin Schuck
Project-URL: Homepage, https://github.com/amacati/SoulsGym
Project-URL: Documentation, https://soulsgym.readthedocs.io/en/latest/
Project-URL: Repository, https://github.com/amacati/SoulsGym
Keywords: gym,reinforcement learning,dark souls
Classifier: License :: OSI Approved :: MIT License
Classifier: Programming Language :: Python
Classifier: Programming Language :: Python :: 3
Classifier: Development Status :: 3 - Alpha
Classifier: Intended Audience :: Developers
Classifier: Intended Audience :: Education
Classifier: Intended Audience :: Science/Research
Requires-Python: >=3.11.2
License-File: LICENSE
Requires-Dist: gymnasium >=0.27.0
Requires-Dist: numpy >=1.21.0
Requires-Dist: psutil >=5.9.0
Requires-Dist: Pymem >=1.10.0
Requires-Dist: PyYAML >=6.0
Requires-Dist: opencv-python >=4.0.0
Requires-Dist: pywin32 >=305.0 ; platform_system == "Windows"
Provides-Extra: test
Requires-Dist: pytest ; extra == 'test'
